igeOpenAL/OpenAL32.dll
igeOpenAL/__init__.py
igeOpenAL/igeOpenAL.cp37-win32.pyd
igeOpenAL-0.0.3.dist-info/LICENSE
igeOpenAL-0.0.3.dist-info/METADATA
igeOpenAL-0.0.3.dist-info/WHEEL
igeOpenAL-0.0.3.dist-info/top_level.txt
igeOpenAL-0.0.3.dist-info/RECORD
