Metadata-Version: 2.1
Name: igeOpenAL
Version: 0.0.3
Summary: C++ extension OpenAL sound for 3D and 2D games.
Home-page: https://indigames.net/
Author: Indigames
Author-email: dev@indigames.net
License: MIT
Keywords: OpenAL 3D game Xiph ogg vorbis opus sound playback audio indigames
Platform: UNKNOWN
Classifier: Intended Audience :: Developers
Classifier: License :: OSI Approved :: MIT License
Classifier: Programming Language :: Python :: 3
Classifier: Operating System :: Microsoft :: Windows
Classifier: Topic :: Games/Entertainment
